{
    "id": 334809,
    "brand": "bandelier",
    "name": "ARTIC",
    "slug": "artic",
    "description": "Artic is a dark chocolate flavored ice cream coating for general use and it is a type of Milk ICC.",
    "company_name": "Blommer Chocolate Company",
    "company_slug": "blommer-chocolate-company",
    "logo_url": "https://media.knowde.com/image/upload/f_auto,q_auto,w_128/v1708673279/production/Brand/24727/logo/image",
    "banner_url": "https://media.knowde.com/image/upload/v1625607274/production/CategoryImage/514/category_image/FoodNutrition_14.jpg",
    "properties": {
        "Applications": [
            "Confectionery",
            "Desserts & Fruit Preparations",
            "Dairy",
            "Food"
        ],
        "Product Families": [
            "Cocoa & Chocolate",
            "Whole Foods, Extracts & Premixes"
        ],
        "End Uses": [
            "Food Coatings",
            "Ice Cream",
            "Compound Ice Cream Coating"
        ]
    },
    "summary": {
        "Ingredient Name": [
            "Dark Chocolate"
        ],
        "Functions": [
            "Food Coating"
        ],
        "Labeling Claims": [
            "Halal",
            "Organic",
            "Non-GMO",
            "Kosher"
        ],
        "Certifications & Compliance": [
            "Fair Trade",
            "Organic Certified",
            "Halal",
            "RSPO Certified Sustainable Palm Oil",
            "Kosher",
            "Non-GMO Project Verified",
            "USDA NOP Certified"
        ]
    }
}