{
    "id": 389636,
    "brand": "komaalu",
    "name": "KömaDur® 276465",
    "slug": "komadur-276465",
    "description": "KömaDur® 276465 is a sheet system of rigid PVC-U. A genuine all-in-one solution for the most diverse requirements. Whether the chemicals industry, the building sector, electrical engineering, exhibitions, or advertising – the five KömaDur variants and their matched material properties are ideally equipped for the most diverse indoor and outdoor applications. In addition, KömaDur scores with properties that make its processing easy and cost effective to boot. KömaDur® 276465 is the child of intensive research and development and over forty years of experience in the extrusion of PVC-U sheets. In all this time, KömaDur has been constantly modified and improved in the face of growing market requirements. The outcome is rigid PVC-U sheets that are characterized by a homogeneous, smooth, and glossy surface quality. They are resistant to flames, chemicals, and corrosion in compliance with DIN 8061 and to most aggressive media.",
    "company_name": "Profine",
    "company_slug": "profine",
    "logo_url": "https://media.knowde.com/image/upload/f_auto,q_auto,w_128/v1686150141/production/Brand/29300/logo/image",
    "banner_url": "https://media.knowde.com/image/upload/v1625608454/production/CategoryImage/560/category_image/BuildingConstruction_04.jpg",
    "properties": {
        "Applications": [
            "Building Materials",
            "Medical",
            "Wall Panels",
            "Displays",
            "Laboratory & Diagnostics",
            "Building Envelope & Roofing",
            "Decorative Materials & Finishes",
            "Wallcoverings & Decorative Laminates",
            "Devices & Assemblies",
            "Chemical & Industrial Manufacturing",
            "Glazing & Window Elements",
            "Other Building Envelope & Roofing Applications",
            "Equipment & Parts"
        ],
        "Product Families": [
            "Parts, Shapes & Films"
        ],
        "Chemical Family": [
            "Vinyls, Vinylics & Vinyl Derivatives"
        ],
        "Polymer Name": [
            "Polyvinyl Chloride (PVC)"
        ],
        "End Uses": [
            "Displays",
            "Wall Panels",
            "3D Printing Applications"
        ]
    },
    "summary": {
        "Polymer Name": [
            "Polyvinyl Chloride (PVC)"
        ],
        "Physical Form": [
            "Sheets"
        ],
        "Features": [
            "Good Weather Stability",
            "Recyclable",
            "High Impact Resistance",
            "Good Printability",
            "Weldable",
            "Glossy Surface Aspects",
            "Flame Resistant",
            "Chemical Resistant",
            "Corrosion Resistant"
        ],
        "Color": [
            "Grey",
            "White"
        ]
    }
}