{
    "id": 407114,
    "brand": "alpha-adhesives-and-sealants-ltd-alpha",
    "name": "Alpha Adhesives and Sealants Ltd A2024 Water-Based Retread Adhesive",
    "slug": "alpha-adhesives-and-sealants-ltd-a2024-water-based-retread-adhesive",
    "description": "Alpha Adhesives and Sealants Ltd A2024 Water-Based Retread Adhesive is a water based adhesive containing a rust inhibitor, suitable for bonding old rubber to new rubber, e.g. in the repair of conveyor belts, or manufacture of retread tires. This product gives enhanced tack for side walling. A2024 also features a built in indicator to determine the correct time to bond the rubber materials during retread.",
    "company_name": "Alpha Adhesives and Sealants",
    "company_slug": "alpha-adhesives-and-sealants-ltd",
    "logo_url": "https://media.knowde.com/image/upload/f_auto,q_auto,w_128/v1682593054/production/Company/13502/logo/image",
    "banner_url": "https://media.knowde.com/image/upload/v1625608438/production/CategoryImage/559/category_image/BuildingConstruction_03.jpg",
    "properties": {
        "Applications": [
            "Tires",
            "Chemical & Industrial Manufacturing",
            "Automotive ",
            "Equipment & Parts"
        ],
        "Product Families": [
            "Adhesives & Sealants",
            "Contact Adhesives"
        ]
    },
    "summary": {
        "Ready to Use Product Type": [
            "Waterborne Adhesive"
        ],
        "Application Area": [
            "Industrial Conveyors",
            "Belts"
        ]
    }
}