{
    "id": 334487,
    "brand": "skyrol",
    "name": "Skyrol® SW84G (92ga) Polyester",
    "slug": "skyrol-sw84g-92ga-polyester",
    "description": "Skyrol® SW84G (92ga) Polyester white opaque polyester film with an adhesion promoting chemical treatment on both sides. It provides enhanced adhesion to coatings, inks and adhesives.SW84G is available in a wide range of thickness from 92ga to 1000ga. SW84G film is FDA approved for direct food contact in compliance with FDA 21 CFR 177.1630 (f).",
    "company_name": "SKC Inc.",
    "company_slug": "skc-inc",
    "logo_url": "https://media.knowde.com/image/upload/f_auto,q_auto,w_128/v1697223692/production/Brand/24658/logo/image",
    "banner_url": "https://media.knowde.com/image/upload/v1625609057/production/CategoryImage/591/category_image/PrintingPackaging_02.jpg",
    "properties": {
        "Applications": [
            "Food & Beverage Packaging",
            "Food Films & Packaging",
            "Flexible Packaging",
            "Packaging"
        ],
        "Product Families": [
            "Parts, Shapes & Films"
        ],
        "Chemical Family": [
            "Polyethylene Terephthalate (PET)"
        ],
        "Polymer Name": [
            "Polyethylene Terephthalate (PET)"
        ],
        "End Uses": [
            "Food Packaging"
        ]
    },
    "summary": {
        "Density": [
            "1500.0 - 1500.0 kg/m³"
        ]
    }
}