{
    "id": 442875,
    "brand": "pro-999-rx-35",
    "name": "Pro-977 Ultra Prime® Primer",
    "slug": "pro-977-ultra-prime-primer",
    "description": "Pro-977 Ultra Prime® Primer is a premium, pigmented water-based primer/sealer. PRO-977 is extremely water resistant, providing an ideal surface for wallcovering installations. PRO-977 is a universal primer which can be used in most applications in place of oil-based primers. Promotes strippability when removing wallcovering.",
    "company_name": "Roman Adhesives",
    "company_slug": "roman-adhesives",
    "logo_url": "https://media.knowde.com/image/upload/f_auto,q_auto,w_128/v1664569106/production/Company/64861/logo/image.png",
    "banner_url": "https://media.knowde.com/image/upload/v1625608410/production/CategoryImage/557/category_image/BuildingConstruction_01.jpg",
    "properties": {
        "Applications": [
            "Wallcoverings & Decorative Laminates",
            "Architectural Coatings",
            "Decorative Materials & Finishes",
            "Building Envelope & Roofing"
        ],
        "Product Families": [
            "Primers & Sealers",
            "Paints & Coatings"
        ],
        "Chemical Family": [
            "Acrylics & Acrylates"
        ]
    },
    "summary": {
        "Ready to Use Product Type": [
            "Primer",
            "Waterborne Coating"
        ],
        "Application Areas": [
            "Wall",
            "Wall Coverings"
        ],
        "Features": [
            "Strong Hiding Power",
            "Mildew Resistant",
            "Low Odor",
            "Water-based",
            "Good Tint Strength",
            "Water Resistant"
        ],
        "Application Method": [
            "Spray",
            "Roller",
            "Brush"
        ],
        "Chemical Family": [
            "Acrylics & Acrylates"
        ]
    }
}