{
    "id": 418276,
    "brand": "glissawax",
    "name": "Glissaspray 8",
    "slug": "glissaspray-8",
    "description": "Glissaspray 8 is a spray micronized fischer-tropsch wax.",
    "company_name": "Parchvale Ltd",
    "company_slug": "parchvale-limited",
    "logo_url": "https://media.knowde.com/image/upload/f_auto,q_auto,w_128/v1708698471/production/Brand/32751/logo/image",
    "banner_url": "https://media.knowde.com/image/upload/f_auto,q_auto,w_512/v1708698471/production/Product/418276/card_banner/image",
    "properties": {
        "Applications": [
            "Textile Manufacturing",
            "Textile Coatings & Inks",
            "Screen Printing",
            "Textiles & Nonwovens",
            "Printing & Inks",
            "Leather & Textiles"
        ],
        "Product Families": [
            "Surface Modifiers",
            "Additives"
        ],
        "Chemical Family": [
            "Waxes",
            "Fischer Tropsch Waxes"
        ],
        "End Uses": [
            "Screen Printing Ink"
        ]
    },
    "summary": {
        "Chemical Family": [
            "Waxes",
            "Fischer Tropsch Waxes"
        ],
        "Functions": [
            "Surface Modifier"
        ],
        "End Uses": [
            "Screen Printing Ink"
        ],
        "Features": [
            "Slip Resistance",
            "Abrasion Resistance",
            "Excellent Scratch Resistance"
        ],
        "Synonyms": [
            "Hydrocarbon waxes, Petroleum waxes"
        ]
    }
}