{
    "id": 441508,
    "brand": "glissawax",
    "name": "Glissamide 14040",
    "slug": "glissamide-14040",
    "description": "Glissamide 14040 is a non-toxic fatty amide synthetic wax of NN Ethylene, Bis Stearamide.",
    "company_name": "Parchvale Ltd",
    "company_slug": "parchvale-limited",
    "logo_url": "https://media.knowde.com/image/upload/f_auto,q_auto,w_128/v1708690166/production/Company/56428/logo/image",
    "banner_url": "https://media.knowde.com/image/upload/f_auto,q_auto,w_512/v1708690166/production/Company/56428/card_banner/image",
    "properties": {
        "Applications": [
            "Coil Coatings",
            "Wood Coatings & Finishes",
            "Building & Construction",
            "Industrial Coatings"
        ],
        "Product Families": [
            "Surface Modifiers",
            "Additives"
        ],
        "Chemical Family": [
            "Waxes",
            "Synthetic Waxes"
        ],
        "End Uses": [
            "Waterborne Coating",
            "Powder Coating",
            "Coil Coating"
        ]
    },
    "summary": {
        "Functions": [
            "Surface Modifier"
        ],
        "Chemical Family": [
            "Waxes",
            "Synthetic Waxes"
        ],
        "End Uses": [
            "Waterborne Coating",
            "Powder Coating",
            "Coil Coating"
        ],
        "Labeling Claims": [
            "Non-Toxic"
        ]
    }
}