{
    "id": 300697,
    "brand": "antiskin",
    "name": "Organo Zn 10",
    "slug": "organo-zn-10",
    "description": "Organo Zn 10 is a low viscosity yellow colored clear solution of zinc metal-carboxylate in mineral spirits or methyl esters.",
    "company_name": "Organometal SA",
    "company_slug": "organometal-sa",
    "logo_url": "https://media.knowde.com/image/upload/f_auto,q_auto,w_128/v1708673341/production/Company/24279/logo/image",
    "banner_url": "https://media.knowde.com/image/upload/v1625608621/production/CategoryImage/570/category_image/PaintingsCoatings_06.jpg",
    "properties": {
        "Applications": [
            "Other Printing & Packaging Applications",
            "Other Paints & Coatings Applications"
        ],
        "Product Families": [
            "Functional Additives",
            "Additives"
        ],
        "Chemical Family": [
            "Zinc Salts",
            "Organometallics"
        ],
        "End Uses": [
            "Waterborne Coating",
            "Solventborne Coating"
        ]
    },
    "summary": {
        "Functions": [
            "Drying Agent"
        ],
        "CAS Number": [
            "136-53-8"
        ],
        "Chemical Family": [
            "Organometallics",
            "Zinc Salts"
        ],
        "End Uses": [
            "Waterborne Coating",
            "Solventborne Coating"
        ],
        "Compatible Polymers & Resins": [
            "Alkyds"
        ],
        "Features": [
            "Low Viscosity"
        ]
    }
}