{
    "id": 428245,
    "brand": "moisture-vapor-barrier",
    "name": "Permashield® 2000",
    "slug": "permashield-2000",
    "description": "Permashield 2000 is a two-component, 100% solids, liquid applied Aliphatic Polyurea topcoat. It is specially formulated for a quick curing same day return to service application.",
    "company_name": "Monopole",
    "company_slug": "monopole",
    "logo_url": "https://media.knowde.com/image/upload/f_auto,q_auto,w_128/v1687520484/production/Brand/33978/logo/image",
    "banner_url": "https://media.knowde.com/image/upload/v1625608611/production/CategoryImage/569/category_image/PaintingsCoatings_05.jpg",
    "properties": {
        "Applications": [
            "Flooring & Surfaces",
            "Floor Coatings"
        ],
        "Product Families": [
            "Paints & Coatings",
            "Top Coats"
        ],
        "Chemical Family": [
            "Polyurethanes (PU)"
        ]
    },
    "summary": {
        "Ready-to-Use Product Type": [
            "Solventless & High Solids Coating",
            "2K (2 component) Coating",
            "Top Coat"
        ],
        "Application Area": [
            "Floor"
        ],
        "Features": [
            "Waterproofing",
            "High Gloss",
            "High Solids Content",
            "Abrasion Resistant",
            "UV Resistant",
            "Fast Cure",
            "High Durability",
            "Excellent Hot Tire Pickup Resistance",
            "Good Weather Stability",
            "Chemical Resistant"
        ],
        "Application Method": [
            "Roller",
            "Wipe"
        ],
        "Chemical Family": [
            "Polyurethanes (PU)"
        ]
    }
}