{
    "id": 332057,
    "brand": "astafit",
    "name": "ASTAFIT® OL100",
    "slug": "astafit-ol100",
    "description": "ASTAFIT® OL100 is 10% astaxanthin content . Increased stability of astaxanthin as 5% or 10% oleoresin",
    "company_name": "BDI-BioLife Science",
    "company_slug": "bdi-biolife-science",
    "logo_url": "https://media.knowde.com/image/upload/f_auto,q_auto,w_128/v1708690650/production/Brand/24347/logo/image",
    "banner_url": "https://media.knowde.com/image/upload/v1625607274/production/CategoryImage/514/category_image/FoodNutrition_14.jpg",
    "properties": {
        "Applications": [
            "Nutraceuticals & Supplements",
            "Nutrition & Well Being"
        ],
        "Product Families": [
            "Phytochemicals & Plant Extracts",
            "Nutraceuticals & Supplements"
        ],
        "End Uses": [
            "Dietary Supplements"
        ]
    },
    "summary": {
        "Ingredient Name": [
            "Astaxanthin Oleoresin"
        ],
        "Active Component": [
            "Astaxanthin"
        ],
        "Features": [
            "Blood Glucose Management",
            "Antioxidant Properties",
            "Anti-Inflammatory"
        ],
        "Functions": [
            "Supplement",
            "Dietary Supplement"
        ]
    }
}