{
    "id": 334468,
    "brand": "amplitex",
    "name": "ampliTex™ Fusion 5027-3",
    "slug": "amplitex-fusion-5027-3",
    "description": "ampliTex flax-carbon fusion UD tape is a non-crimp, 120 mm width, 170 gsm",
    "company_name": "Bcomp Ltd.",
    "company_slug": "bcomp",
    "logo_url": "https://media.knowde.com/image/upload/f_auto,q_auto,w_128/v1691741921/production/Brand/24657/logo/image",
    "banner_url": "https://media.knowde.com/image/upload/f_auto,q_auto,w_512/v1691741921/production/Product/334468/card_banner/image",
    "properties": {
        "Applications": [
            "Sports & Recreation",
            "Marine",
            "Aerospace & Aviation",
            "Interior",
            "Transportation",
            "Automotive"
        ],
        "Product Families": [
            "Hybrid Reinforcements",
            "Reinforcements"
        ]
    },
    "summary": {}
}