{
    "id": 339451,
    "brand": "capros",
    "name": "PrimaVie®",
    "slug": "primavie",
    "description": "PrimaVie® is a high quality, clinically studied, Purified Shilajit from the Himalayas, containing dibenzo-α-pyrones (DBPs), DBP-Chromoproteins (DCP), Fulvic Acid and over 40 different minerals. Its’ history of use goes back to The Indus Valley Civilization, 3,000 B.C., where British archeologists have found evidence of use of Shilajit, which is considered the greatest rasayana in Ayurveda. PrimaVie® is an ideal anti-aging product.",
    "company_name": "Natreon",
    "company_slug": "natreon",
    "logo_url": "https://media.knowde.com/image/upload/f_auto,q_auto,w_128/v1697223104/production/Brand/24979/logo/image",
    "banner_url": "https://media.knowde.com/image/upload/v1625606914/production/CategoryImage/502/category_image/FoodNutrition_03.jpg",
    "properties": {
        "Applications": [
            "Nutraceuticals & Supplements",
            "Nutrition & Well Being"
        ],
        "Product Families": [
            "Supplements & Functional Ingredients",
            "Functional Ingredients",
            "Phytochemicals & Plant Extracts",
            "Nutrition & Fortification",
            "Nutraceuticals & Supplements"
        ],
        "End Uses": [
            "Dietary Supplements"
        ]
    },
    "summary": {}
}