{
    "id": 469403,
    "brand": "ginkgoselect",
    "name": "Indena Artichoke",
    "slug": "indena-artichoke",
    "description": "Indena Artichoke is a dry extract obtained from the leaves of Cynara cardunculus L. This product is used in the nutraceuticals industry for its benefits for cholesterol and intestinal health. It contains 6 - 12% of caffeoylquinic acids, as calculated by HPLC. This product is halal- and kosher-certified.",
    "company_name": "Indena",
    "company_slug": "indena",
    "logo_url": "https://media.knowde.com/image/upload/f_auto,q_auto,w_128/v1708695961/production/Company/1265/logo/image",
    "banner_url": "https://media.knowde.com/image/upload/f_auto,q_auto,w_512/v1708695961/production/Company/1265/card_banner/image",
    "properties": {
        "Applications": [
            "Nutraceuticals & Supplements",
            "Nutrition & Well Being"
        ],
        "Product Families": [
            "Vegetable Products & Extracts",
            "Functional Ingredients",
            "Supplements & Functional Ingredients",
            "Phytochemicals & Plant Extracts",
            "Phytochemicals",
            "Nutrition & Fortification",
            "Whole Foods, Extracts & Premixes",
            "Nutraceuticals & Supplements"
        ],
        "Ingredient Name": [
            "Artichoke Extract"
        ]
    },
    "summary": {
        "Ingredient Name": [
            "Artichoke Extract"
        ],
        "Active Component": [
            "5-Caffeoylquinic Acid"
        ],
        "Functions": [
            "Phytochemical"
        ],
        "Ingredient Origin": [
            "Natural Origin",
            "Plant Origin"
        ],
        "Labeling Claims": [
            "Plant-Based",
            "Halal",
            "Kosher",
            "Naturally Derived"
        ],
        "Certifications & Compliance": [
            "Halal",
            "Kosher"
        ]
    }
}