{
    "id": 373654,
    "brand": "soudabond",
    "name": "Soudabond Easy gun foam",
    "slug": "soudabond-easy-gun-foam",
    "description": "Soudabond Easy gun foam is a ready-to-use, single component, self-expanding polyurethane adhesive for clean, efficient and economical permanent bonding of insulation panels and plasterboard in building and construction.",
    "company_name": "Soudal USA",
    "company_slug": "soudal",
    "logo_url": "https://media.knowde.com/image/upload/f_auto,q_auto,w_128/v1687520020/production/Brand/27897/logo/image",
    "banner_url": "https://media.knowde.com/image/upload/v1625608438/production/CategoryImage/559/category_image/BuildingConstruction_03.jpg",
    "properties": {
        "Applications": [
            "Building Materials",
            "Construction Chemicals",
            "Wall Panels",
            "Adhesives",
            "Construction Adhesives"
        ],
        "Product Families": [
            "Adhesives & Sealants",
            "Other Adhesives & Sealants"
        ],
        "Chemical Family": [
            "Polyurethanes (PU)"
        ]
    },
    "summary": {
        "Ready-to-Use Product Type": [
            "1K (1 component) Sealant"
        ],
        "Compatible Substrates & Surfaces": [
            "Wood",
            "Concrete",
            "Plastics",
            "Polystyrene (PS)"
        ],
        "Cure Method": [
            "Moisture Cure"
        ],
        "Chemical Family": [
            "Polyurethanes (PU)"
        ]
    }
}