{
    "id": 304393,
    "brand": "mayron",
    "name": "MAYRENE® MW222 U",
    "slug": "mayrene-mw222-u",
    "description": "MAYRENE® MW222 U is Polystyrene (PS) grade product.",
    "company_name": "Metro Wealth Polymer",
    "company_slug": "metro-wealth-polymer",
    "logo_url": "https://media.knowde.com/image/upload/f_auto,q_auto,w_128/v1708528630/production/Company/13674/logo/image",
    "banner_url": "https://static.knowde.com/card-banners/knowde-card-for-raw-materials-8.jpg",
    "properties": {
        "Applications": [
            "Other Printing & Packaging Applications",
            "Other Electrical & Electronics Applications",
            "Other Consumer Goods Applications",
            "Other Automotive & Transportation Applications"
        ],
        "Product Families": [
            "Styrenics",
            "Basic Thermoplastics"
        ],
        "Chemical Family": [
            "Styrenics",
            "High-Impact Polystyrene (HIPS)"
        ],
        "Polymer Name": [
            "High Impact Polystyrene (HIPS)"
        ]
    },
    "summary": {
        "Polymer Name": [
            "High Impact Polystyrene (HIPS)"
        ],
        "Melt Flow Index": [
            "4.0 - 8.0 g/10 min"
        ]
    }
}