{
    "id": 412314,
    "brand": "thermo-lite-board",
    "name": "Thermo-Lite Board® Tough",
    "slug": "thermo-lite-board-tough",
    "description": "Thermo-Lite Board®Tough is manufactured with polymer foam and a heavy-weight woven fiberglass lay-up, this product is acceptable for standard structural loading applications. Available in a density range of 24 to 44 lbs/ft³ depending upon the thickness required.",
    "company_name": "Space Age Synthetics Inc.",
    "company_slug": "space-age-synthetics-inc",
    "logo_url": "https://media.knowde.com/image/upload/f_auto,q_auto,w_128/v1702444510/production/Brand/32173/logo/image",
    "banner_url": "https://media.knowde.com/image/upload/v1625608693/production/CategoryImage/573/category_image/AutomotiveTransportation_01.jpg",
    "properties": {
        "Applications": [
            "Other Automotive & Transportation Applications",
            "Marine",
            "Transportation"
        ],
        "Product Families": [
            "Foams"
        ],
        "Chemical Family": [
            "Polyurethanes (PU)"
        ],
        "End Uses": [
            "Automotive Trim",
            "Marine Applications"
        ]
    },
    "summary": {
        "Foam Type": [
            "Closed Cell Foam"
        ],
        "Chemical Family": [
            "Polyurethanes (PU)"
        ],
        "End Uses": [
            "Marine Applications",
            "Automotive Trim"
        ],
        "Physical Form": [
            "Foam"
        ]
    }
}